.coveragerc
.gitignore
AUTHORS.rst
CHANGES.rst
LICENSE.txt
README.md
extract.py
requirements.txt
setup.cfg
setup.py
test-requirements.txt
docs/Makefile
docs/authors.rst
docs/changes.rst
docs/conf.py
docs/index.rst
docs/license.rst
docs/_static/.gitignore
srtvoiceext/__init__.py
srtvoiceext/extractor.py
srtvoiceext/skeleton.py
srtvoiceext/utils.py
srtvoiceext.egg-info/PKG-INFO
srtvoiceext.egg-info/SOURCES.txt
srtvoiceext.egg-info/dependency_links.txt
srtvoiceext.egg-info/entry_points.txt
srtvoiceext.egg-info/requires.txt
srtvoiceext.egg-info/top_level.txt
tests/conftest.py
tests/test_skeleton.py